{
    "eeg_producer__10_10_2024__09_14_21": {
        "states": [
            [
                0,
                32640,
                36480
            ],
            [
                0,
                69248,
                73088
            ],
            [
                0,
                150912,
                154752
            ],
            [
                0,
                270208,
                274048
            ],
            [
                0,
                287488,
                291328
            ],
            [
                2,
                162944,
                166784
            ]
        ],
        "segment label": [
            [
                [
                    32896,
                    36736
                ],
                [
                    34176,
                    35456
                ],
                "IES"
            ],
            [
                [
                    55168,
                    59008
                ],
                [
                    34176,
                    35456
                ],
                "IES"
            ],
            [
                [
                    55168,
                    59008
                ],
                [
                    56448,
                    57728
                ],
                "IES"
            ]
        ]
    },
    "eeg_producer__10_10_2024__10_17_23": {
        "states": [
            [
                0,
                0,
                3840
            ],
            [
                0,
                37376,
                41216
            ]
        ]
    },
    "rec_20240125_094414": {
        "states": [
            [
                21,
                0,
                86272
            ]
        ],
        "segment label": [
            [
                [
                    0,
                    1792
                ],
                [
                    585,
                    616
                ],
                "Eye artifacts"
            ],
            [
                [
                    0,
                    1792
                ],
                [
                    616,
                    981
                ],
                "Large artefacts"
            ],
            [
                [
                    0,
                    1792
                ],
                [
                    1338,
                    1372
                ],
                "Eye artifacts"
            ],
            [
                [
                    0,
                    1792
                ],
                [
                    1394,
                    1456
                ],
                "Eye artifacts"
            ],
            [
                [
                    0,
                    1792
                ],
                [
                    1484,
                    1731
                ],
                "Large artefacts"
            ],
            [
                [
                    1792,
                    3584
                ],
                [
                    2021,
                    3488
                ],
                "Large artefacts"
            ],
            [
                [
                    4096,
                    5888
                ],
                [
                    4306,
                    5879
                ],
                "Large artefacts"
            ],
            [
                [
                    4096,
                    5888
                ],
                [
                    5166,
                    5204
                ],
                "Eye artifacts"
            ],
            [
                [
                    4096,
                    5888
                ],
                [
                    5498,
                    5567
                ],
                "Eye artifacts"
            ],
            [
                [
                    6656,
                    8448
                ],
                [
                    7331,
                    7375
                ],
                "Eye artifacts"
            ],
            [
                [
                    6656,
                    8448
                ],
                [
                    7732,
                    7791
                ],
                "Eye artifacts"
            ],
            [
                [
                    6656,
                    8448
                ],
                [
                    8013,
                    8072
                ],
                "Eye artifacts"
            ],
            [
                [
                    6656,
                    8448
                ],
                [
                    7942,
                    7999
                ],
                "Eye artifacts"
            ]
        ]
    }
}